README.md
setup.cfg
setup.py
localstack_extension_snowflake.egg-info/PKG-INFO
localstack_extension_snowflake.egg-info/SOURCES.txt
localstack_extension_snowflake.egg-info/dependency_links.txt
localstack_extension_snowflake.egg-info/entry_points.txt
localstack_extension_snowflake.egg-info/not-zip-safe
localstack_extension_snowflake.egg-info/requires.txt
localstack_extension_snowflake.egg-info/top_level.txt
snowflake_local/__init__.py
snowflake_local/config.py
snowflake_local/constants.py
snowflake_local/extension.py
snowflake_local/analytics/__init__.py
snowflake_local/analytics/handler.py
snowflake_local/engine/__init__.py
snowflake_local/engine/constants.py
snowflake_local/engine/db_engine.py
snowflake_local/engine/models.py
snowflake_local/engine/packages.py
snowflake_local/engine/queries.py
snowflake_local/engine/query_processors.py
snowflake_local/engine/session.py
snowflake_local/engine/transform_utils.py
snowflake_local/engine/transforms.py
snowflake_local/engine/postgres/__init__.py
snowflake_local/engine/postgres/constants.py
snowflake_local/engine/postgres/db_engine_postgres.py
snowflake_local/engine/postgres/db_state.py
snowflake_local/engine/processors/__init__.py
snowflake_local/engine/processors/aggregates.py
snowflake_local/engine/processors/aliases.py
snowflake_local/engine/processors/arrays.py
snowflake_local/engine/processors/conversions.py
snowflake_local/engine/processors/datetime.py
snowflake_local/engine/processors/errors.py
snowflake_local/engine/processors/formats.py
snowflake_local/engine/processors/functions.py
snowflake_local/engine/processors/identifiers.py
snowflake_local/engine/processors/json.py
snowflake_local/engine/processors/keys.py
snowflake_local/engine/processors/metadata.py
snowflake_local/engine/processors/session.py
snowflake_local/engine/processors/shares.py
snowflake_local/engine/processors/stages.py
snowflake_local/engine/processors/storage.py
snowflake_local/engine/processors/streams.py
snowflake_local/engine/processors/subqueries.py
snowflake_local/engine/processors/system.py
snowflake_local/engine/processors/tasks.py
snowflake_local/engine/processors/types.py
snowflake_local/engine/processors/variants.py
snowflake_local/engine/processors/windows.py
snowflake_local/files/__init__.py
snowflake_local/files/file_ops.py
snowflake_local/files/staging.py
snowflake_local/files/storage.py
