Metadata-Version: 2.1
Name: localstack-extension-snowflake
Version: 0.1.23
Summary: LocalStack Extension: Snowflake
Home-page: https://localstack.cloud
Author: LocalStack
Author-email: support@localstack.cloud
Provides-Extra: dev
Provides-Extra: test
